neural_network/__init__.py
neural_network/nn/__init__.py
neural_network/nn/core.py
neural_network/utils/__init__.py
neural_network/utils/utillties.py
self_designed_NeuralNetwork-0.0.1.dist-info/LICENSE
self_designed_NeuralNetwork-0.0.1.dist-info/METADATA
self_designed_NeuralNetwork-0.0.1.dist-info/WHEEL
self_designed_NeuralNetwork-0.0.1.dist-info/top_level.txt
self_designed_NeuralNetwork-0.0.1.dist-info/RECORD
